CodeCraft/__init__.py
CodeCraft/Compilation/__init__.py
CodeCraft/Definition/__init__.py
CreatePro-1.0.6.data/scripts/entry.py
CreatePro-1.0.6.dist-info/LICENSE
CreatePro-1.0.6.dist-info/METADATA
CreatePro-1.0.6.dist-info/WHEEL
CreatePro-1.0.6.dist-info/top_level.txt
CreatePro-1.0.6.dist-info/zip-safe
CreatePro-1.0.6.dist-info/RECORD
